deepracer/__init__.py
deepracer/__main__.py
deepracer/_version.py
deepracer/utils.py
deepracer/boto3_enhancer/__init__.py
deepracer/boto3_enhancer/models/deepracer/2019-04-01/service-2.json
deepracer/console/__init__.py
deepracer/console/helper.py
deepracer/logs/__init__.py
deepracer/logs/handler.py
deepracer/logs/log.py
deepracer/logs/log_utils.py
deepracer/logs/metrics.py
deepracer/logs/misc.py
deepracer/model/__init__.py
deepracer/model/visualization.py
deepracer/tracks/__init__.py
deepracer/tracks/track_utils.py
deepracer/update_action_speeds/action_space.json
deepracer/update_action_speeds/updateActionSpeeds.py
deepracer_utils-1.0.11.dist-info/LICENSE
deepracer_utils-1.0.11.dist-info/METADATA
deepracer_utils-1.0.11.dist-info/WHEEL
deepracer_utils-1.0.11.dist-info/top_level.txt
deepracer_utils-1.0.11.dist-info/RECORD
