Metadata-Version: 2.1
Name: deepracer-utils
Version: 1.0.11
Summary: A set of tools for working with DeepRacer training
Home-page: https://github.com/aws-deepracer-community/deepracer-utils/
Author: AWS DeepRacer Community
License: UNKNOWN
Project-URL: Bug Reports, https://github.com/aws-deepracer-community/deepracer-utils/issues
Project-URL: Source, https://github.com/aws-deepracer-community/deepracer-utils/
Keywords: aws deepracer awsdeepracer
Platform: UNKNOWN
Classifier: Development Status :: 5 - Production/Stable
Classifier: License :: OSI Approved :: MIT No Attribution License (MIT-0)
Classifier: Programming Language :: Python :: 3.8
Classifier: Programming Language :: Python :: 3.9
Classifier: Programming Language :: Python :: 3.10
Classifier: Programming Language :: Python :: 3.11
Classifier: Programming Language :: Python :: 3.12
Classifier: Topic :: Internet :: Log Analysis
Requires-Python: >=3.8,<4.0
License-File: LICENSE
Requires-Dist: boto3 >=1.12.0
Requires-Dist: joblib >=0.17.0
Requires-Dist: matplotlib >=3.1.0
Requires-Dist: numpy >=1.18.0
Requires-Dist: pandas >=1.0.0
Requires-Dist: python-dateutil <3.0.0,>=2.1
Requires-Dist: scikit-learn >=0.22.0
Requires-Dist: shapely >=1.7.0
Provides-Extra: dev
Requires-Dist: check-manifest ; extra == 'dev'
Provides-Extra: test
Requires-Dist: coverage ; extra == 'test'
Requires-Dist: opencv-python ; extra == 'test'
Requires-Dist: python-resize-image ; extra == 'test'
Requires-Dist: tensorflow ; extra == 'test'
Provides-Extra: visualization
Requires-Dist: opencv-python ; extra == 'visualization'
Requires-Dist: python-resize-image ; extra == 'visualization'
Requires-Dist: tensorflow ; extra == 'visualization'
